{
  "content": [
    {
      "kind": "section",
      "title": "Läbiv teema „Elukestev õpe ja karjääri planeerimine“",
      "children": [
        {
          "kind": "text",
          "html": "<ul><li>Õpilasi valmistatakse ette õpingute jätkamiseks ja enesetäiendamiseks.</li><li>Õpilastele antakse suuniseid tulevase ameti valikul.</li></ul>"
        }
      ]
    },
    {
      "kind": "section",
      "title": "Läbiva teema „Keskkond ja jätkusuutlik areng“",
      "children": [
        {
          "kind": "text",
          "html": "<ul><li>Käsitletakse inimtegevuse mõju keskkonnale läbi ajaloo.</li><li>Kujundatakse keskkonda säästvat mõtteviisi.</li></ul>"
        }
      ]
    },
    {
      "kind": "section",
      "title": "Läbiv teema „Kodanikualgatus ja ettevõtlikkus“",
      "children": [
        {
          "kind": "text",
          "html": "<ul><li>Õpilasi suunatakse mõtlema ja arutlema kodukoha ning riigi arengu ja probleemide üle.</li><li>Ajalootunnid annavad hea võimaluse innustada õpilasi täitma kodanikukohust (nt osalema valimistel ja kaasava eelarve hääletustel jne).</li><li>Kujundatakse soovi väärtustada kodukoha ajaloolist miljööd ja kultuuriväärtusi.</li></ul>"
        }
      ]
    },
    {
      "kind": "section",
      "title": "Läbiv teema „Kultuuriline identiteet“",
      "children": [
        {
          "kind": "text",
          "html": "<ul><li>Tutvustatakse eestluse kujunemist läbi ajaloo.</li><li>Kasvatatakse oma rahvuskultuuri ja kultuuripärandit hindavaid kodanikke.</li><li>Õpetatakse hindama teisi rahvusi ja kultuure.</li></ul>"
        }
      ]
    },
    {
      "kind": "section",
      "title": "Läbiv teema „Teabekeskkond“",
      "children": [
        {
          "kind": "text",
          "html": "<ul><li>Info otsimiseks õpetatakse kasutama erinevaid internetikeskkondi.</li><li>Suunatakse kasutama erinevaid teavikuid.</li><li>Suunatakse eri infoallikatesse kriitiliselt suhtuma.</li></ul>"
        }
      ]
    },
    {
      "kind": "section",
      "title": "Läbiv teema „Tehnoloogia ja innovatsioon“",
      "children": [
        {
          "kind": "text",
          "html": "<ul><li>Tutvustatakse tehnoloogia arengut läbi aegade.</li><li>Selgitatakse, kuidas innovatsioon on mõjutanud inimkonna ajaloo kulgu.</li></ul>"
        }
      ]
    },
    {
      "kind": "section",
      "title": "Läbiv teema „Tervis ja ohutus“",
      "children": [
        {
          "kind": "text",
          "html": "<ul><li>Käsitletakse inimese tervisekäitumist läbi ajaloo.</li><li>Õpetatakse hindama tervist säästvaid harjumusi ja käitumist.</li></ul>"
        }
      ]
    },
    {
      "kind": "section",
      "title": "Läbiv teema „Väärtused ja kõlblus“",
      "children": [
        {
          "kind": "text",
          "html": "<ul><li>Õpetatakse hindama demokraatlikke väärtusi.</li><li>Õpetatakse viisakalt ja teisi arvestavalt avaldama oma arvamust, seisukohti ja väärtushinnanguid.</li><li>Õpetatakse arvestama teistsuguseid arvamusi, seisukohti ja väärtushinnanguid.</li></ul>"
        }
      ]
    }
  ]
}
