{
  "content": [
    {
      "kind": "section",
      "title": "",
      "children": [
        {
          "kind": "text",
          "html": "<ul><li>Kasuta konkreetseid, ühe- kuni kolmesõnalisi lihtlauseid.</li><li>Esita üks korraldus, sõnum korraga.</li><li>Suuna korraldus, sõnum konkreetsele õpilasele.</li><li>Anna õpilasele vastavalt vajadusele aega reageerimiseks ja vastamiseks.</li><li>Saada tegevusi kõnega, selgita keskkonna muudatusi.</li><li>Toeta oma verbaalset kõne visuaalsete abivahenditega nt osutamine, žestid, PCS (ingl k <em>Picture Communication Symbols</em>) pildid.</li><li>Osad õpilased (nt autismispektrihäirega e ASH-ga õpilased) toetuvad info saamisel pigem visuaalsele kui auditiivsele infole. Sellisel juhul võib õppetegevus toimuda pigem vaikuses, kus õpetaja juhendab õpilasi osutades (esemele, keskkonnale, pildile), viibeldes, koos või kordamööda tegutsedes.</li><li>Anna õpilasele positiivset tagasisidet.</li></ul>"
        }
      ]
    },
    {
      "kind": "section",
      "title": "NB!",
      "children": [
        {
          "kind": "text",
          "html": "<p>Kui õpetaja on liiga aktiivne, siis õpilane ainult reageerib, tal ei saa areneda initsiatiiv, omaalgatus.</p>"
        }
      ]
    },
    {
      "kind": "section",
      "title": "Juhendamise raskusastmed on:",
      "children": [
        {
          "kind": "text",
          "html": "<ul><li>sooritab füüsilise abiga;</li><li>sooritab osutava viipe alusel;</li><li>sooritab ettenäitamisel;</li><li>sooritab näidise järgi;</li><li>sooritab suulisel juhendamisel ja/või alternatiivkommunikatsiooni (AAC) vahendi abil.</li></ul>"
        }
      ]
    },
    {
      "kind": "section",
      "title": "NB!",
      "children": [
        {
          "kind": "text",
          "html": "<p>Õpilasele korralduse edastamine ei ole juhendamine.</p>"
        }
      ]
    }
  ]
}
