{
  "content": [
    {
      "kind": "section",
      "title": "2.1 Üldõpetuse (tervikõppe) põhimõtete rakendamine ja lõiming hooldusõppes",
      "children": [
        {
          "kind": "text",
          "html": "<p>Tervikõppe peamiseks printsiibiks on õppimine läbi loomulike tegevuste, arvestades päeva rütmi ja õpilaste vajadusi. Tervikõppe teljeks on sotsiaalsed ja eakohased praktilised tegevused. Erinevad tegevusvaldkonnad (kognitiivsed oskused, kommunikatsioon, sotsiaalsed oskused, igapäevaoskused, motoorika) on tervikõppes omavahel lõimitud ning piirid nende vahel on raskesti eristatavad. Näiteks teelauas harjutatakse igapäevaoskusi (laua katmine, koristamine, võileiva valmistamine), kommunikatiivseid oskusi (soovi väljendamine), sotsiaalseid oskusi (ühine alustamise/lõpetamise rituaal), motoorseid oskusi (tee valamine) ja kognitiivseid oskusi (lõhna-, maitse-, tekstuuriaistingud, valikute tegemine). Tingimusi, mida igapäevaste oskuste õpetamiseks vaja läheb (pood, ülekäigurada) ei ole mõistlik simuleerida, sest õpilane ei pruugi kanda õppekeskkonnas omandatud oskusi üle igapäevaellu. Loomulik situatsioon annab õpilasele motivatsiooni ja oskuse õpitut sarnases olukorras rakendada.</p>"
        },
        {
          "kind": "text",
          "html": "<p>Heaks näiteks tervikõppest on hommikuring. See on päeva lahutamatu osa, mille peamiseks eesmärgiks on sisse juhatada algav koolipäev, häälestada õpilane koostööks klassis ja anda teada, mis teda päeva jooksul ees ootab. Hommikuringi oluline eesmärk on sotsialiseerumine. Olles kaaslastega koos, tekib õlg-õla kõrval tunne, suheldakse üksteisega tuttavatel teemadel, kuulatakse ära üksteise uudised. Hommikuringis pööratakse tähelepanu sellele, kes on kohal ja kes puuduvad, mis päev, kuu ja aastaaeg parasjagu käimas on. Hommikuringil on oma kindel struktuur, kuid teemade käsitlusviis ja raskusaste võivad eri päevadel pisut erineda.</p>"
        }
      ]
    }
  ]
}
